[
    {
        "question": "Translate the following phrase: 'Good morning'",
        "video": "M7lc1UVf-VE",
        "start": 30,
        "end": 40,
        "answers": [
            "Buenos días",
            "Buena noche",
            "Buenas tardes",
            "Buenas noches"
        ],
        "correct": 0
    },
    {
        "question": "Translate the following phrase: 'Thank you'",
        "video": "M7lc1UVf-VE",
        "start": 40,
        "end": 50,
        "answers": [
            "Gracias",
            "De nada",
            "Lo siento",
            "Por favor"
        ],
        "correct": 0
    },
    // Add more questions as needed
]
